{
	"name": "PL_CPY_SQL",
	"properties": {
		"activities": [
			{
				"name": "Lookup1",
				"type": "Lookup",
				"dependsOn": [],
				"policy": {
					"timeout": "0.12:00:00",
					"retry": 0,
					"retryIntervalInSeconds": 30,
					"secureOutput": false,
					"secureInput": false
				},
				"userProperties": [],
				"typeProperties": {
					"source": {
						"type": "JsonSource",
						"storeSettings": {
							"type": "AzureBlobFSReadSettings",
							"recursive": true,
							"enablePartitionDiscovery": false
						},
						"formatSettings": {
							"type": "JsonReadSettings"
						}
					},
					"dataset": {
						"referenceName": "Json1",
						"type": "DatasetReference",
						"parameters": {
							"container_name": "manual-files",
							"file_name": "Table_Source_SQL.json"
						}
					},
					"firstRowOnly": false
				}
			},
			{
				"name": "ForEach1",
				"type": "ForEach",
				"dependsOn": [
					{
						"activity": "Lookup1",
						"dependencyConditions": [
							"Succeeded"
						]
					}
				],
				"userProperties": [],
				"typeProperties": {
					"items": {
						"value": "@activity('Lookup1').output.value",
						"type": "Expression"
					},
					"activities": [
						{
							"name": "Copy data1",
							"type": "Copy",
							"dependsOn": [],
							"policy": {
								"timeout": "0.12:00:00",
								"retry": 0,
								"retryIntervalInSeconds": 30,
								"secureOutput": false,
								"secureInput": false
							},
							"userProperties": [],
							"typeProperties": {
								"source": {
									"type": "AzureSqlSource",
									"queryTimeout": "02:00:00",
									"partitionOption": "None"
								},
								"sink": {
									"type": "DelimitedTextSink",
									"storeSettings": {
										"type": "AzureBlobFSWriteSettings"
									},
									"formatSettings": {
										"type": "DelimitedTextWriteSettings",
										"quoteAllText": true,
										"fileExtension": ".txt"
									}
								},
								"enableStaging": false,
								"translator": {
									"type": "TabularTranslator",
									"typeConversion": true,
									"typeConversionSettings": {
										"allowDataTruncation": true,
										"treatBooleanAsNumber": false
									}
								}
							},
							"inputs": [
								{
									"referenceName": "AzureSqlTable1",
									"type": "DatasetReference",
									"parameters": {
										"tablename": {
											"value": "@item().tablename_source",
											"type": "Expression"
										}
									}
								}
							],
							"outputs": [
								{
									"referenceName": "Dataset_CSV_Sink",
									"type": "DatasetReference",
									"parameters": {
										"File_name_sink": {
											"value": "@item().filename_sink",
											"type": "Expression"
										},
										"container_sink": "raw",
										"directory_sink": {
											"value": "@concat(item().tablename_source,'/Date_Part=',formatDateTime(utcnow(),'yyyy-MM-dd'))\n",
											"type": "Expression"
										}
									}
								}
							]
						}
					]
				}
			}
		],
		"annotations": []
	}
}